Workbook

Sheet Dashboard
B2: eBay DE — Go-Live Checklist
B3: CCP × A.B.S. · Channable 314525 · eBay kanaal 159122 · launch-week 2026-07-14 t/m 2026-07-18 · bron: golive-checklist-status.json
B5: Items totaal | C5: Done | D5: Doing | E5: To do | F5: % klaar | G5: Blockers open
B6: =COUNTA(Checklist!B2:B32) -> 31 | C6: =COUNTIF(Checklist!I2:I32,"done") -> 18 | D6: =COUNTIF(Checklist!I2:I32,"doing") -> 6 | E6: =COUNTIF(Checklist!I2:I32,"todo") -> 7 | F6: =COUNTIF(Checklist!I2:I32,"done")/COUNTA(Checklist!B2:B32) -> 0.58064516 | G6: =COUNTIFS(Checklist!H2:H32,"Ja",Checklist!I2:I32,"<>done") -> 10
B8: =IF(COUNTIFS(Checklist!H2:H32,"Ja",Checklist!I2:I32,"<>done")=0,"✔ GO — alle go-live-blockers af","✖ NO-GO — "&COUNTIFS(Checklist!H2:H32,"Ja",Checklist!I2:I32,"<>done")&" blocker-items open") -> ✖ NO-GO — 10 blocker-items open
B10: Voortgang per gate
B11: Gate | C11: Done | D11: Doing | E11: To do | F11: Blockers open | G11: Status
B12: =Gates!A2&" · "&Gates!B2 -> G0 · Infra hersteld (storeview-incident) | C12: =Gates!D2 -> 3 | D12: =Gates!E2 -> 0 | E12: =Gates!F2 -> 1 | F12: =Gates!G2 -> 1 | G12: =Gates!H2 -> NO-GO (1 open)
B13: =Gates!A3&" · "&Gates!B3 -> G1 · Legal / compliance | C13: =Gates!D3 -> 2 | D13: =Gates!E3 -> 1 | E13: =Gates!F3 -> 1 | F13: =Gates!G3 -> 2 | G13: =Gates!H3 -> NO-GO (2 open)
B14: =Gates!A4&" · "&Gates!B4 -> G2 · Order loopt door | C14: =Gates!D4 -> 3 | D14: =Gates!E4 -> 0 | E14: =Gates!F4 -> 0 | F14: =Gates!G4 -> 0 | G14: =Gates!H4 -> GO
B15: =Gates!A5&" · "&Gates!B5 -> G3 · Verzending + T&T | C15: =Gates!D5 -> 1 | D15: =Gates!E5 -> 1 | E15: =Gates!F5 -> 1 | F15: =Gates!G5 -> 2 | G15: =Gates!H5 -> NO-GO (2 open)
B16: =Gates!A6&" · "&Gates!B6 -> G4 · Factuur — GEEN go-live-blocker (besluit Hans 10-07; B2C niet verplicht, B2B binnen 6 mnd op verzoek) | C16: =Gates!D6 -> 0 | D16: =Gates!E6 -> 0 | E16: =Gates!F6 -> 2 | F16: =Gates!G6 -> 0 | G16: =Gates!H6 -> GO
B17: =Gates!A7&" · "&Gates!B7 -> G5 · Retour | C17: =Gates!D7 -> 2 | D17: =Gates!E7 -> 1 | E17: =Gates!F7 -> 0 | F17: =Gates!G7 -> 1 | G17: =Gates!H7 -> NO-GO (1 open)
B18: =Gates!A8&" · "&Gates!B8 -> G6 · Listings kloppen | C18: =Gates!D8 -> 4 | D18: =Gates!E8 -> 1 | E18: =Gates!F8 -> 0 | F18: =Gates!G8 -> 0 | G18: =Gates!H8 -> GO
B19: =Gates!A9&" · "&Gates!B9 -> G7 · Betaling & policies | C19: =Gates!D9 -> 1 | D19: =Gates!E9 -> 0 | E19: =Gates!F9 -> 1 | F19: =Gates!G9 -> 1 | G19: =Gates!H9 -> NO-GO (1 open)
B20: =Gates!A10&" · "&Gates!B10 -> G8 · Eindtest + launch-week | C20: =Gates!D10 -> 2 | D20: =Gates!E10 -> 2 | E20: =Gates!F10 -> 1 | F20: =Gates!G10 -> 3 | G20: =Gates!H10 -> NO-GO (3 open)
B22: Besluit Hans 10-07: factuur (G4) = geen go-live-blocker (grijs/cursief in Checklist). Kritieke pad: G0 → G1 → 6.4 (SKU Filter, Hans) → 8.1 (Uitvoeren, Hans).

Sheet Checklist
A1: Gate | B1: ID | C1: Taak | D1: Definition of Done | E1: Verificatiemethode | F1: Owner | G1: Fase | H1: Go-live blocker | I1: Status | J1: Bewijs / evidence | K1: Laatst gecheckt
A2: G0 · Infra hersteld | B2: 0.1 | C2: Atvise: Magento scope/storeview rollback | D2: Channable Magento-import Items > 0 | E2: API: import 750543 item-count | F2: Atvise | G2: Pre-live | H2: Ja | I2: done | J2: Duitse Store draait inactief ernaast. Channable op default store werkend. (Hans 10-07) | K2: 2026-07-10
A3: G0 · Infra hersteld | B3: 0.2 | C3: Verzendmethode DE aan (Ship to Applicable Countries, juiste scope) | D3: DE-testorder importeert zonder 'verzendmethode ontbreekt' | E3: API + VIS Magento config | F3: Hans/Luca | G3: Pre-live | H3: Ja | I3: done | J3: Order eBay→Channable→Magento bewezen op order 144013198 (Hans 10-07) | K3: 2026-07-10
A4: G0 · Infra hersteld | B4: 0.3 | C4: 13 mislukte testorders opnieuw versturen | D4: 0 orders in Mislukte bestellingen | E4: VIS Channable Orders | F4: Hans | G4: Pre-live | H4: Ja | I4: todo | J4: Niet in Hans' status-update 10-07; flow werkt inmiddels (144013198) — resterende testorder-errors in Channable opruimen of afvoeren | K4: 2026-07-10
A5: G0 · Infra hersteld | B5: 0.4 | C5: Besluit: live zonder DE-storeview | D5: Besluit gelogd in vault | E5: SIGN Hans+Sjoerd | F5: Hans | G5: Pre-live | H5: Ja | I5: done | J5: Besluit: live via default store; DE-storeview staat (inactief) voor 3 productcategorieën ernaast (Hans 10-07) | K5: 2026-07-10
A6: G1 · Legal / compliance | B6: 1.1 | C6: Impressum · AGB · Widerruf · Datenschutz live | D6: 4 teksten zichtbaar op eBay-shop/listings | E6: VIS eBay shop | F6: Sjoerd | G6: Pre-live | H6: Ja | I6: todo | J6: [unverified] — 4 wk stil per actieplan 07-06 | K6: 2026-07-10
A7: G1 · Legal / compliance | B7: 1.2 | C7: OSS actief, 19% DE-btw op listing + factuur | D7: Bevestiging adviseur op schrift | E7: SIGN | F7: Sjoerd | G7: Pre-live | H7: Ja | I7: doing | J7: OSS actief; DE-btw hoeft niet op factuur zolang OSS actief. BTW-proces loopt. (Hans 10-07) | K7: 2026-07-10
A8: G1 · Legal / compliance | B8: 1.3 | C8: Lizenzero/VerpackG getekend + LUCID-nr | D8: Contract + LUCID-nummer in dossier | E8: SIGN + doc | F8: Sjoerd | G8: Pre-live | H8: Ja | I8: done | J8: LUCID DE5131761082554; Lizenzero/VerpackG getekend, binnen 09-07-2026 (Hans 10-07) | K8: 2026-07-10
A9: G1 · Legal / compliance | B9: 1.4 | C9: GPSR op elke listing (Tinbergenlaan 7, veld gpsr_manufacturer_name) | D9: Compliance Dashboard 0 rood; GPSR in preview | E9: VIS Seller Hub + API feedcheck | F9: Hans | G9: Pre-live | H9: Ja | I9: done | J9: GPSR in alle 20 regels (setup-status 07-08); door Hans afgetekend 10-07 | K9: 2026-07-10
A10: G2 · Order loopt door | B10: 2.1 | C10: Allow Countries = DE (herbevestigen na incident) | D10: DE-adres geaccepteerd bij import | E10: API/VIS | F10: Hans/Luca | G10: Pre-live | H10: Ja | I10: done | J10: Gezet 07-07; herbevestigd via order 144013198 op 10-07 (Hans) | K10: 2026-07-10
A11: G2 · Order loopt door | B11: 2.2 | C11: eBay order-sync Complete actief in Channable | D11: Connectie Active + shipment updates Enabled | E11: API order-config | F11: Hans | G11: Pre-live | H11: Ja | I11: done | J11: Stoplicht-A4 07-07: Active + Enabled | K11: 2026-07-08
A12: G2 · Order loopt door | B12: 2.3 | C12: DE-testorder in Magento én D365 | D12: Order zichtbaar in Magento + D365-sync bevestigd | E12: E2E + SIGN Niek | F12: Hans/Niek | G12: Pre-live | H12: Ja | I12: done | J12: DE-testorder in Magento bewezen (144013198); D365-sync via Niek (Hans 10-07) | K12: 2026-07-10
A13: G3 · Verzending + T&T | B13: 3.1 | C13: DPD DE-label + tarief (schijven >5kg marge >15%) | D13: Testlabel gegenereerd, marge-check gelogd | E13: VIS + SIGN | F13: Hans | G13: Pre-live | H13: Ja | I13: todo | K13: 2026-07-10
A14: G3 · Verzending + T&T | B14: 3.2 | C14: ABS API vult T&T op shipment bij álle orders | D14: 3 opeenvolgende orders met gevuld trackingveld | E14: VIS Magento Shipments steekproef | F14: Niek | G14: Pre-live | H14: Ja | I14: done | J14: Afgetekend Hans 10-07. NB bewijs-dossier: 1 testorder gevuld (DPD 05112095164869); DoD was 3 opeenvolgende orders — steekproef blijft in launch-week | K14: 2026-07-10
A15: G3 · Verzending + T&T | B15: 3.3 | C15: Tracking terug op eBay + carrier 'DPD' (default staat op DPD Predict) | D15: Trackingnr klikbaar op eBay-order, koper gemaild | E15: E2E + VIS | F15: Hans | G15: Pre-live | H15: Ja | I15: doing | J15: Transporter-regel ≥13→DPD staat; propagatie afwachten op order 144013198 (geplaatst 10-07) | K15: 2026-07-10
A16: G4 · Factuur | B16: 4.1 | C16: Besluit factuurpad (B2C geen / Billbee / easybill) | D16: Besluit gelogd | E16: SIGN Sjoerd | F16: Sjoerd | G16: Na live | H16: Nee | I16: todo | J16: NA LIVE — geen blocker (Hans 10-07). Advies ligt er sinds 07-06 (order-to-cash + factuur-opties-A4) | K16: 2026-07-10
A17: G4 · Factuur | B17: 4.2 | C17: Indien tool: koppelen, 19%/OSS, test-B2B-factuur | D17: 1 correcte factuur op testorder | E17: E2E + VIS | F17: Hans | G17: Na live | H17: Nee | I17: todo | J17: NA LIVE — geen blocker. Wacht op 4.1 | K17: 2026-07-10
A18: G5 · Retour | B18: 5.1 | C18: eBay retourbeleid (30 dgn) + retouradres + provider | D18: Policy zichtbaar op listing | E18: VIS | F18: Hans | G18: Pre-live | H18: Ja | I18: done | J18: Afgetekend Hans 10-07 | K18: 2026-07-10
A19: G5 · Retour | B19: 5.2 | C19: Returnless-config afmaken (validatie→postcode, formulier, DE→NL label, Dev-integratie los) | D19: Testretour vindt order op postcode | E19: E2E Returnless | F19: Hans | G19: Pre-live | H19: Ja | I19: doing | J19: Insteladvies 10-07: integratie AAN, importer UIT correct; 3 punten open + laatste scope-check | K19: 2026-07-10
A20: G5 · Retour | B20: 5.3 | C20: Verwerker refund aangewezen | D20: Naam gelogd | E20: SIGN | F20: Sjoerd | G20: Pre-live | H20: Ja | I20: done | J20: Luca & Hans, zelfde proces als webshop (Hans 10-07) | K20: 2026-07-10
A21: G6 · Listings kloppen | B21: 6.1 | C21: Titels Duits ≤80 (20 kanaalregels) | D21: 0 titels >80 op go-live-scope | E21: API preview scope-SKU's | F21: Hans | G21: Pre-live | H21: Ja | I21: done | J21: log.md 07-08: 20 titels hercheck, max 77 | K21: 2026-07-08
A22: G6 · Listings kloppen | B22: 6.2 | C22: Omschrijving met GPSR, geen lege velden | D22: Preview 3 SKU per categorie schoon | E22: VIS preview | F22: Hans | G22: Pre-live | H22: Ja | I22: done | J22: Setup-status 07-08: 20 regels, GPSR uit veld | K22: 2026-07-08
A23: G6 · Listings kloppen | B23: 6.3 | C23: eBay-categorie per product juist | D23: Go-live-SKU's 100% gecategoriseerd | E23: API | F23: Hans | G23: Pre-live | H23: Ja | I23: done | J23: 78,1% feed-breed, 0 mapping-mismatches; afgetekend Hans 10-07 | K23: 2026-07-10
A24: G6 · Listings kloppen | B24: 6.4 | C24: SKU Filter = exact de bedoelde go-live-lijst (kostenrem — alleen Hans) | D24: Item-teller preview = bedoeld aantal | E24: API items-na + SIGN Hans | F24: Hans | G24: Pre-live | H24: Ja | I24: done | J24: Afgetekend Hans 10-07. NB: scope = 4 test-SKU's — bevestig dat dít de bedoelde livegang-lijst is vóór Uitvoeren | K24: 2026-07-10
A25: G6 · Listings kloppen | B25: 6.5 | C25: Item-specifics live categorieën (OE/Vergleich/EAN/Einbauposition); maten zodra Bremsscheiben live | D25: Attributes-pagina gemapt voor alle live categorieën | E25: VIS Build→Attributes | F25: Hans | G25: Pre-live | H25: Nee | I25: doing | J25: 3 categorieën gemapt 07-08; maten + K-Typ open. Geen blocker — wel nodig voor eBay Partsfinder; optimalisatie ná live (Hans 10-07) | K25: 2026-07-10
A26: G7 · Betaling & policies | B26: 7.1 | C26: Managed Payments payout-config (bank, EUR, schema) | D26: Payout-status actief in Seller Hub | E26: VIS | F26: Hans | G26: Pre-live | H26: Ja | I26: todo | K26: 2026-07-10
A27: G7 · Betaling & policies | B27: 7.2 | C27: Business Policies (Shipping ≤2 dgn, Payment, Return) aan alle listings | D27: Policies-pagina toont koppeling | E27: VIS | F27: Hans | G27: Pre-live | H27: Ja | I27: done | J27: Afgetekend Hans 10-07 | K27: 2026-07-10
A28: G8 · Eindtest + launch-week | B28: 8.1 | C28: Hans klikt Uitvoeren (nooit de agent) | D28: Listings live op eBay DE | E28: SIGN Hans + VIS | F28: Hans | G28: Pre-live | H28: Ja | I28: todo | K28: 2026-07-10
A29: G8 · Eindtest + launch-week | B29: 8.2 | C29: 1 echte order: betaald → verzonden → getrackt → (gefactureerd) | D29: Alle stappen met bewijs | E29: E2E | F29: Hans | G29: Pre-live | H29: Ja | I29: doing | J29: Echte order onderweg (144013198) — E2E-bewijs volgt | K29: 2026-07-10
A30: G8 · Eindtest + launch-week | B30: 8.3 | C30: 1 retour getest end-to-end | D30: Refund verwerkt | E30: E2E | F30: Hans | G30: Pre-live | H30: Ja | I30: doing | J30: Huidige route wordt getest (Hans 10-07) | K30: 2026-07-10
A31: G8 · Eindtest + launch-week | B31: 8.4 | C31: Launch-week order-watch 14–18/7 actief | D31: Task enabled + eerste run gelogd | E31: API scheduled-tasks | F31: Cowork | G31: Pre-live | H31: Ja | I31: done | J31: ebay-de-launch-order-watch enabled, next run 14-07 08:07 | K31: 2026-07-10
A32: G8 · Eindtest + launch-week | B32: 8.5 | C32: Na live: Messages, INR/SNAD-proces, Verkäufer-Cockpit, out-of-stock-control | D32: Proces + eigenaar gelogd | E32: SIGN | F32: Hans/Luca | G32: Na live | H32: Nee | I32: done | J32: Hans → Marketplace manager (Hans 10-07) | K32: 2026-07-10

Sheet Gates
A1: Gate | B1: Omschrijving | C1: Items | D1: Done | E1: Doing | F1: To do | G1: Blockers open | H1: Gate-status (GO / NO-GO)
A2: G0 | B2: Infra hersteld (storeview-incident) | C2: =COUNTIF(Checklist!$A$2:$A$32,"G0 ·*") -> 4 | D2: =COUNTIFS(Checklist!$A$2:$A$32,"G0 ·*",Checklist!$I$2:$I$32,"done") -> 3 | E2: =COUNTIFS(Checklist!$A$2:$A$32,"G0 ·*",Checklist!$I$2:$I$32,"doing") -> 0 | F2: =COUNTIFS(Checklist!$A$2:$A$32,"G0 ·*",Checklist!$I$2:$I$32,"todo") -> 1 | G2: =COUNTIFS(Checklist!$A$2:$A$32,"G0 ·*",Checklist!$H$2:$H$32,"Ja",Checklist!$I$2:$I$32,"<>done") -> 1 | H2: =IF(G2=0,"GO","NO-GO ("&G2&" open)") -> NO-GO (1 open)
A3: G1 | B3: Legal / compliance | C3: =COUNTIF(Checklist!$A$2:$A$32,"G1 ·*") -> 4 | D3: =COUNTIFS(Checklist!$A$2:$A$32,"G1 ·*",Checklist!$I$2:$I$32,"done") -> 2 | E3: =COUNTIFS(Checklist!$A$2:$A$32,"G1 ·*",Checklist!$I$2:$I$32,"doing") -> 1 | F3: =COUNTIFS(Checklist!$A$2:$A$32,"G1 ·*",Checklist!$I$2:$I$32,"todo") -> 1 | G3: =COUNTIFS(Checklist!$A$2:$A$32,"G1 ·*",Checklist!$H$2:$H$32,"Ja",Checklist!$I$2:$I$32,"<>done") -> 2 | H3: =IF(G3=0,"GO","NO-GO ("&G3&" open)") -> NO-GO (2 open)
A4: G2 | B4: Order loopt door | C4: =COUNTIF(Checklist!$A$2:$A$32,"G2 ·*") -> 3 | D4: =COUNTIFS(Checklist!$A$2:$A$32,"G2 ·*",Checklist!$I$2:$I$32,"done") -> 3 | E4: =COUNTIFS(Checklist!$A$2:$A$32,"G2 ·*",Checklist!$I$2:$I$32,"doing") -> 0 | F4: =COUNTIFS(Checklist!$A$2:$A$32,"G2 ·*",Checklist!$I$2:$I$32,"todo") -> 0 | G4: =COUNTIFS(Checklist!$A$2:$A$32,"G2 ·*",Checklist!$H$2:$H$32,"Ja",Checklist!$I$2:$I$32,"<>done") -> 0 | H4: =IF(G4=0,"GO","NO-GO ("&G4&" open)") -> GO
A5: G3 | B5: Verzending + T&T | C5: =COUNTIF(Checklist!$A$2:$A$32,"G3 ·*") -> 3 | D5: =COUNTIFS(Checklist!$A$2:$A$32,"G3 ·*",Checklist!$I$2:$I$32,"done") -> 1 | E5: =COUNTIFS(Checklist!$A$2:$A$32,"G3 ·*",Checklist!$I$2:$I$32,"doing") -> 1 | F5: =COUNTIFS(Checklist!$A$2:$A$32,"G3 ·*",Checklist!$I$2:$I$32,"todo") -> 1 | G5: =COUNTIFS(Checklist!$A$2:$A$32,"G3 ·*",Checklist!$H$2:$H$32,"Ja",Checklist!$I$2:$I$32,"<>done") -> 2 | H5: =IF(G5=0,"GO","NO-GO ("&G5&" open)") -> NO-GO (2 open)
A6: G4 | B6: Factuur — GEEN go-live-blocker (besluit Hans 10-07; B2C niet verplicht, B2B binnen 6 mnd op verzoek) | C6: =COUNTIF(Checklist!$A$2:$A$32,"G4 ·*") -> 2 | D6: =COUNTIFS(Checklist!$A$2:$A$32,"G4 ·*",Checklist!$I$2:$I$32,"done") -> 0 | E6: =COUNTIFS(Checklist!$A$2:$A$32,"G4 ·*",Checklist!$I$2:$I$32,"doing") -> 0 | F6: =COUNTIFS(Checklist!$A$2:$A$32,"G4 ·*",Checklist!$I$2:$I$32,"todo") -> 2 | G6: =COUNTIFS(Checklist!$A$2:$A$32,"G4 ·*",Checklist!$H$2:$H$32,"Ja",Checklist!$I$2:$I$32,"<>done") -> 0 | H6: =IF(G6=0,"GO","NO-GO ("&G6&" open)") -> GO
A7: G5 | B7: Retour | C7: =COUNTIF(Checklist!$A$2:$A$32,"G5 ·*") -> 3 | D7: =COUNTIFS(Checklist!$A$2:$A$32,"G5 ·*",Checklist!$I$2:$I$32,"done") -> 2 | E7: =COUNTIFS(Checklist!$A$2:$A$32,"G5 ·*",Checklist!$I$2:$I$32,"doing") -> 1 | F7: =COUNTIFS(Checklist!$A$2:$A$32,"G5 ·*",Checklist!$I$2:$I$32,"todo") -> 0 | G7: =COUNTIFS(Checklist!$A$2:$A$32,"G5 ·*",Checklist!$H$2:$H$32,"Ja",Checklist!$I$2:$I$32,"<>done") -> 1 | H7: =IF(G7=0,"GO","NO-GO ("&G7&" open)") -> NO-GO (1 open)
A8: G6 | B8: Listings kloppen | C8: =COUNTIF(Checklist!$A$2:$A$32,"G6 ·*") -> 5 | D8: =COUNTIFS(Checklist!$A$2:$A$32,"G6 ·*",Checklist!$I$2:$I$32,"done") -> 4 | E8: =COUNTIFS(Checklist!$A$2:$A$32,"G6 ·*",Checklist!$I$2:$I$32,"doing") -> 1 | F8: =COUNTIFS(Checklist!$A$2:$A$32,"G6 ·*",Checklist!$I$2:$I$32,"todo") -> 0 | G8: =COUNTIFS(Checklist!$A$2:$A$32,"G6 ·*",Checklist!$H$2:$H$32,"Ja",Checklist!$I$2:$I$32,"<>done") -> 0 | H8: =IF(G8=0,"GO","NO-GO ("&G8&" open)") -> GO
A9: G7 | B9: Betaling & policies | C9: =COUNTIF(Checklist!$A$2:$A$32,"G7 ·*") -> 2 | D9: =COUNTIFS(Checklist!$A$2:$A$32,"G7 ·*",Checklist!$I$2:$I$32,"done") -> 1 | E9: =COUNTIFS(Checklist!$A$2:$A$32,"G7 ·*",Checklist!$I$2:$I$32,"doing") -> 0 | F9: =COUNTIFS(Checklist!$A$2:$A$32,"G7 ·*",Checklist!$I$2:$I$32,"todo") -> 1 | G9: =COUNTIFS(Checklist!$A$2:$A$32,"G7 ·*",Checklist!$H$2:$H$32,"Ja",Checklist!$I$2:$I$32,"<>done") -> 1 | H9: =IF(G9=0,"GO","NO-GO ("&G9&" open)") -> NO-GO (1 open)
A10: G8 | B10: Eindtest + launch-week | C10: =COUNTIF(Checklist!$A$2:$A$32,"G8 ·*") -> 5 | D10: =COUNTIFS(Checklist!$A$2:$A$32,"G8 ·*",Checklist!$I$2:$I$32,"done") -> 2 | E10: =COUNTIFS(Checklist!$A$2:$A$32,"G8 ·*",Checklist!$I$2:$I$32,"doing") -> 2 | F10: =COUNTIFS(Checklist!$A$2:$A$32,"G8 ·*",Checklist!$I$2:$I$32,"todo") -> 1 | G10: =COUNTIFS(Checklist!$A$2:$A$32,"G8 ·*",Checklist!$H$2:$H$32,"Ja",Checklist!$I$2:$I$32,"<>done") -> 3 | H10: =IF(G10=0,"GO","NO-GO ("&G10&" open)") -> NO-GO (3 open)
B11: TOTAAL | C11: =SUM(C2:C10) -> 31 | D11: =SUM(D2:D10) -> 18 | E11: =SUM(E2:E10) -> 6 | F11: =SUM(F2:F10) -> 7 | G11: =SUM(G2:G10) -> 10 | H11: =IF(G11=0,"GO — verantwoord live","NO-GO ("&G11&" blockers open)") -> NO-GO (10 blockers open)

Sheet Audit trail
A1: Tijdstip | B1: Run | C1: Door | D1: Samenvatting | E1: Wijzigingen
A2: 2026-07-10T14:30:00+02:00 | B2: init | C2: cowork-interactief | D2: Initiële vulling uit vault-synthese 10-07. Done 4 · Doing 11 · To do 16. | E2: alle items aangemaakt
A3: 2026-07-10T15:10:00+02:00 | B3: correctie-hans | C3: cowork-interactief | D3: Besluit Hans: factuur (Gate 4) is GEEN go-live-blocker — verplaatst naar na-live. Kritieke pad = G0, G1, 6.4, 8.1. Channable-API-koppeling voorbereid via _skill/adapters/.env (CHANNABLE_*). | E3: G4 hernoemd, 4.1/4.2 evidence NA LIVE
A4: 2026-07-10T15:25:00+02:00 | B4: memory-sync | C4: cowork-interactief | D4: 0.4 storeview-besluit → done (stond al vast in memory). Done 5 · Doing 10 · To do 16. | E4: 0.4 done
A5: 2026-07-10T17:05:00+02:00 | B5: hans-status-sync | C5: cowork-interactief | D5: Volledige status-sync met Hans' tabel 10-07 (SIGN Hans autoritair). Done 18 · Doing 6 · To do 7. 6.5 hergemarkeerd als niet-blocker. Aandachtspunten: 3.2 (DoD 3 orders, dossier 1), 6.4 (scope=4 SKU's bevestigen), 0.3 ontbrak in tabel. | E5: 20 items bijgewerkt

Sheet Legenda
B2: Legenda & werkwijze
B3: Status | C3: todo = nog niet gestart · doing = loopt · done = af (kies via dropdown in Checklist, kolom I)
B4: Go-live blocker | C4: Ja = moet af vóór Uitvoeren · Nee = mag ná live (G4 factuur + 8.5, besluit Hans 10-07; grijs/cursief)
B5: Verificatiemethode | C5: API = Channable/Magento API-check · VIS = screenshot/UI-bewijs · SIGN = handmatige sign-off (naam+datum) · E2E = end-to-end testtransactie
B6: GO / NO-GO | C6: Gate = GO zodra alle blocker-items van die gate done zijn. Dashboard toont totaal-verdict.
B7: Bron & sync | C7: Digitale bron = golive-status/golive-checklist-status.json (dagelijkse audit-task 07:25 werkt JSON + LIVE-HTML + Gmail-concept bij). Deze Excel is de deel-/werkversie; wijzigingen die moeten blijven ook in de JSON doorvoeren.
B8: Harde regels | C8: SKU Filter alleen lezen (kostenrem) · 'Uitvoeren' klikt alleen Hans (8.1) · SIGN-items nooit automatisch done · API-keys uit _skill/adapters/.env
B9: Kleuren | C9: Groen = done · Oranje = doing · Rood = todo · Groene cijfers op Dashboard = links naar andere werkbladen
